setup.cfg
setup.py
fenced_code_plus/__init__.py
fenced_code_plus/fenced_code_plus.py
fenced_code_plus/test_fenced_code_plus.py
fenced_code_plus.egg-info/PKG-INFO
fenced_code_plus.egg-info/SOURCES.txt
fenced_code_plus.egg-info/dependency_links.txt
fenced_code_plus.egg-info/requires.txt
fenced_code_plus.egg-info/top_level.txt