Metadata-Version: 1.0
Name: fenced-code-plus
Version: 0.1.2
Summary: A markdown extension for adding additional attributes to fenced code.
Home-page: https://github.com/amfarrell/fenced-code-plus
Author: Andrew M. Farrell
Author-email: amfarrell@mit.edu
License: UNKNOWN
Keywords: code format,fenced code,markdown
Platform: UNKNOWN
